[
  {
    "ContainingType": "JobPortal.API.Controllers.JobApplicationsController",
    "Method": "ApplyJob",
    "RelativePath": "api/applications/apply",
    "HttpMethod": "POST",
    "IsController": true,
    "Order": 0,
    "Parameters": [
      {
        "Name": "dto",
        "Type": "JobPortal.API.DTOs.ApplyJobDto",
        "IsRequired": true
      }
    ],
    "ReturnTypes": []
  },
  {
    "ContainingType": "JobPortal.API.Controllers.JobApplicationsController",
    "Method": "GetApplicantsForJob",
    "RelativePath": "api/applications/job/{jobId}",
    "HttpMethod": "GET",
    "IsController": true,
    "Order": 0,
    "Parameters": [
      {
        "Name": "jobId",
        "Type": "System.Int32",
        "IsRequired": true
      }
    ],
    "ReturnTypes": []
  },
  {
    "ContainingType": "JobPortal.API.Controllers.JobApplicationsController",
    "Method": "GetMyAppliedJobs",
    "RelativePath": "api/applications/my",
    "HttpMethod": "GET",
    "IsController": true,
    "Order": 0,
    "Parameters": [],
    "ReturnTypes": []
  },
  {
    "ContainingType": "JobPortal.API.Controllers.AuthController",
    "Method": "GetClaims",
    "RelativePath": "api/auth/claims",
    "HttpMethod": "GET",
    "IsController": true,
    "Order": 0,
    "Parameters": [],
    "ReturnTypes": []
  },
  {
    "ContainingType": "JobPortal.API.Controllers.AuthController",
    "Method": "Login",
    "RelativePath": "api/auth/login",
    "HttpMethod": "POST",
    "IsController": true,
    "Order": 0,
    "Parameters": [
      {
        "Name": "request",
        "Type": "JobPortal.API.DTOs.LoginRequestDto",
        "IsRequired": true
      }
    ],
    "ReturnTypes": []
  },
  {
    "ContainingType": "JobPortal.API.Controllers.AuthController",
    "Method": "GetProfile",
    "RelativePath": "api/auth/profile",
    "HttpMethod": "GET",
    "IsController": true,
    "Order": 0,
    "Parameters": [],
    "ReturnTypes": []
  },
  {
    "ContainingType": "JobPortal.API.Controllers.AuthController",
    "Method": "Register",
    "RelativePath": "api/auth/register",
    "HttpMethod": "POST",
    "IsController": true,
    "Order": 0,
    "Parameters": [
      {
        "Name": "user",
        "Type": "JobPortal.API.Models.User",
        "IsRequired": true
      }
    ],
    "ReturnTypes": []
  },
  {
    "ContainingType": "JobPortal.API.Controllers.JobsController",
    "Method": "GetAllJobs",
    "RelativePath": "api/jobs",
    "HttpMethod": "GET",
    "IsController": true,
    "Order": 0,
    "Parameters": [],
    "ReturnTypes": []
  },
  {
    "ContainingType": "JobPortal.API.Controllers.JobsController",
    "Method": "PostJob",
    "RelativePath": "api/jobs",
    "HttpMethod": "POST",
    "IsController": true,
    "Order": 0,
    "Parameters": [
      {
        "Name": "dto",
        "Type": "JobPortal.API.DTOs.CreateJobDto",
        "IsRequired": true
      }
    ],
    "ReturnTypes": []
  },
  {
    "ContainingType": "JobPortal.API.Controllers.ResumeController",
    "Method": "UploadResume",
    "RelativePath": "api/resume/upload",
    "HttpMethod": "POST",
    "IsController": true,
    "Order": 0,
    "Parameters": [
      {
        "Name": "resume",
        "Type": "Microsoft.AspNetCore.Http.IFormFile",
        "IsRequired": false
      }
    ],
    "ReturnTypes": []
  },
  {
    "ContainingType": "JobPortal.API.Controllers.WeatherForecastController",
    "Method": "Get",
    "RelativePath": "WeatherForecast",
    "HttpMethod": "GET",
    "IsController": true,
    "Order": 0,
    "Parameters": [],
    "ReturnTypes": [
      {
        "Type": "System.Collections.Generic.IEnumerable\u00601[[JobPortal.API.WeatherForecast, JobPortal.API, Version=1.0.0.0, Culture=neutral, PublicKeyToken=null]]",
        "MediaTypes": [
          "text/plain",
          "application/json",
          "text/json"
        ],
        "StatusCode": 200
      }
    ],
    "EndpointName": "GetWeatherForecast"
  }
]